unidoc_agent/__init__.py
unidoc_agent/agent.py
unidoc_agent/base_tool.py
unidoc_agent/ollama_client.py
unidoc_agent/tests/__init__.py
unidoc_agent/tests/test_agent.py
unidoc_agent/tools/__init__.py
unidoc_agent/tools/code_tool.py
unidoc_agent/tools/email_tool.py
unidoc_agent/tools/excel_tool.py
unidoc_agent/tools/ocr_tool.py
unidoc_agent/tools/pdf_tool.py
unidoc_agent/tools/text_tool.py
unidoc_agent/tools/word_tool.py
unidoc_agent/tools/xml_tool.py
unidoc_agent-0.2.6.dist-info/LICENSE
unidoc_agent-0.2.6.dist-info/METADATA
unidoc_agent-0.2.6.dist-info/WHEEL
unidoc_agent-0.2.6.dist-info/top_level.txt
unidoc_agent-0.2.6.dist-info/RECORD
